edasuite/__init__.py
edasuite/eda.py
edasuite/py.typed
edasuite/analyzers/__init__.py
edasuite/analyzers/basic.py
edasuite/analyzers/categorical.py
edasuite/analyzers/continuous.py
edasuite/analyzers/stability.py
edasuite/analyzers/target_analysis.py
edasuite/core/__init__.py
edasuite/core/base.py
edasuite/core/correlation.py
edasuite/core/exceptions.py
edasuite/core/feature_processor.py
edasuite/core/loader.py
edasuite/core/logging_config.py
edasuite/core/missing.py
edasuite/core/performance.py
edasuite/core/schema_mapper.py
edasuite/core/types.py
edasuite/output/__init__.py
edasuite/output/formatter.py
edasuite-0.0.3.dist-info/licenses/LICENSE
edasuite-0.0.3.dist-info/METADATA
edasuite-0.0.3.dist-info/WHEEL
edasuite-0.0.3.dist-info/top_level.txt
edasuite-0.0.3.dist-info/RECORD
